csft/__init__.py
csft/__main__.py
csft/_csft.py
csft/_meta.py
csft-0.4.0.dist-info/DESCRIPTION.rst
csft-0.4.0.dist-info/METADATA
csft-0.4.0.dist-info/RECORD
csft-0.4.0.dist-info/WHEEL
csft-0.4.0.dist-info/entry_points.txt
csft-0.4.0.dist-info/metadata.json
csft-0.4.0.dist-info/top_level.txt
