Metadata-Version: 2.0
Name: csft
Version: 0.4.0
Summary: Count Sizes of File Types
Home-page: https://github.com/yanqd0/csft
Author: Yan QiDong
Author-email: yanqd0@outlook.com
License: MIT License
Keywords: CLI
Platform: any
Classifier: Development Status :: 3 - Alpha
Classifier: Environment :: Console
Classifier: Intended Audience :: Developers
Classifier: License :: OSI Approved :: MIT License
Classifier: Operating System :: MacOS :: MacOS X
Classifier: Operating System :: Microsoft :: Windows
Classifier: Operating System :: POSIX :: Linux
Classifier: Programming Language :: Python :: 2.7
Classifier: Programming Language :: Python :: 3.3
Classifier: Programming Language :: Python :: 3.4
Classifier: Programming Language :: Python :: 3.5
Classifier: Programming Language :: Python :: 3.6
Requires-Python: >=2.7, !=3.0.*, !=3.1.*, !=3.2.*, !=3.3.*
Requires-Dist: pandas (>=0.20.3)
Requires-Dist: humanfriendly (>=4.6)
